flask_github_issues/__init__.py
flask_github_issues/tracker.py
flask_github_issues-0.1.5.dist-info/licenses/LICENSE
tests/__init__.py
tests/test_tracker.py
flask_github_issues-0.1.5.dist-info/METADATA
flask_github_issues-0.1.5.dist-info/WHEEL
flask_github_issues-0.1.5.dist-info/top_level.txt
flask_github_issues-0.1.5.dist-info/RECORD
