Metadata-Version: 2.4
Name: flask-github-issues
Version: 0.1.5
Summary: A Python package for tracking Flask errors via GitHub Issues.
Home-page: https://github.com/Pontem-Innovations/flask-github-issues
Author: Pontem Innovations
Author-email: geoff@ponteminnovations.ca
Classifier: Programming Language :: Python :: 3
Classifier: License :: OSI Approved :: MIT License
Classifier: Operating System :: OS Independent
Requires-Python: >=3.6
License-File: LICENSE
Requires-Dist: requests
Requires-Dist: pytz
Requires-Dist: user-agents
Dynamic: author
Dynamic: author-email
Dynamic: classifier
Dynamic: description
Dynamic: description-content-type
Dynamic: home-page
Dynamic: license-file
Dynamic: requires-dist
Dynamic: requires-python
Dynamic: summary
